{
  "name" : "Mazumdar Shaw Medical Center, Bommasandra",
  "specialties" : [ {
    "name" : "Anaesthesia & Critical Care",
    "schedules" : [ {
      "doctor" : "Amit Misra",
      "degree" : "MBBS, DNB",
      "designation" : "Junior Consultant",
      "schedule" : "Mon to Sat: By Appointment"
    }, {
      "doctor" : "Arjun Alva",
      "degree" : "MD, Fellowship",
      "designation" : "Consultant",
      "schedule" : "Mon to Sat: By Appointment"
    }, {
      "doctor" : "Harish B R",
      "degree" : "MBBS, MD",
      "designation" : "Consultant",
      "schedule" : "Mon to Sat: By Appointment"
    }, {
      "doctor" : "Harish Mallapura Maheswarappa",
      "degree" : "MD, DNB, IDCCM, DM",
      "designation" : "Consultant",
      "schedule" : "Mon to Sat: By Appointment"
    }, {
      "doctor" : "Hemant H R",
      "degree" : "MBBS, MD (Anaesthesiology), Internal Quality Auditor - ACLS (Provider), ACLS (Instructor), FNB (Critical care medicine)",
      "designation" : "Senior Consultant",
      "schedule" : "Mon to Sat: By Appointment"
    }, {
      "doctor" : "Jinay Gala",
      "degree" : "MBBS, DNB (Medicine)",
      "designation" : "Consultant",
      "schedule" : "Mon to Sat: By Appointment"
    }, {
      "doctor" : "Murugesan C",
      "degree" : "MD",
      "designation" : "Senior Consultant",
      "schedule" : "Mon to Sat: By Appointment"
    }, {
      "doctor" : "Nausheen Saba",
      "degree" : "MBBS, Fellow in Critical Care Medicine",
      "designation" : "Senior Registrar",
      "schedule" : "Mon to Sat: By Appointment"
    }, {
      "doctor" : "Naveena K",
      "degree" : "MD",
      "designation" : "Consultant",
      "schedule" : "Mon to Sat: By Appointment"
    }, {
      "doctor" : "Sanjay Kumar Bc",
      "degree" : "MD",
      "designation" : "Senior Consultant",
      "schedule" : "Mon to Sat: By Appointment"
    }, {
      "doctor" : "Shyamala Devi C",
      "degree" : "DA, IDCCM",
      "designation" : "Consultant",
      "schedule" : "Mon to Sat: By Appointment"
    }, {
      "doctor" : "Vimal Bhardwaj D",
      "degree" : "MD, Fellowship (Critical Care Medicine)",
      "designation" : "Consultant",
      "schedule" : "Mon to Sat: By Appointment"
    } ]
  }, {
    "name" : "Bone Marrow Transplant",
    "schedules" : [ {
      "doctor" : "Nataraj Ks",
      "degree" : "MBBS, MD (Internal Medicine), DM (Clinical Hematology & Hematology Oncology, Stem Cell Transplantation)",
      "designation" : "Consultant - Hematology, Hematology - Oncology, Stem Cell Transplant Physician",
      "schedule" : "Mon to Sat: By Appointment"
    }, {
      "doctor" : "Pooja Prakash Mallya",
      "degree" : "MBBS, MD",
      "designation" : "Associate Consultant",
      "schedule" : "Mon to Sat: By Appointment"
    }, {
      "doctor" : "Sharat Damodar",
      "degree" : "DNB (General Medicine), MD, DM (Haematology)",
      "designation" : "Vice Chairman - Oncology Services, Clinical Director - Msmc Senior Consultant & Head Of Adult Haematology And Bmt",
      "schedule" : "Mon to Sat: By Appointment"
    }, {
      "doctor" : "Shilpa Prabhu",
      "degree" : "MBBS, MD, DNB",
      "designation" : "Consultant - Haemato - Oncology",
      "schedule" : "Mon to Sat: By Appointment"
    }, {
      "doctor" : "Shobha Badiger",
      "degree" : "MBBS, MD (Paediatric), DNB (Paediatric), Fellowship in Comprehensive Hemato Oncology, PGDMLE",
      "designation" : "Consultant",
      "schedule" : "Mon to Sat: By Appointment"
    }, {
      "doctor" : "Sunil Bhat",
      "degree" : "MBBS, MD, FPHO",
      "designation" : "Director & Clinical Lead - Paediatric Hematology, Oncology And Blood & Bone Marrow Transplantation",
      "schedule" : "Mon to Sat: By Appointment"
    }, {
      "doctor" : "Vasundhara Kailasnath Posavanika",
      "degree" : "MD, DM, MD, Fellowship Pediatric Hematology, Oncology and Stem Cell Transplantation",
      "designation" : "Consultant",
      "schedule" : "Mon to Sat: By Appointment"
    } ]
  }, {
    "name" : "Breast Cancer",
    "schedules" : [ {
      "doctor" : "Akshita Singh",
      "degree" : "MRCS, DNB (General Surgery), Fellowship (Breast Surgical)",
      "designation" : "Consultant",
      "schedule" : "Mon to Sat: By Appointment"
    } ]
  }, {
    "name" : "Clinical Nutrition & Dietetics",
    "schedules" : [ {
      "doctor" : "Emmany D R",
      "degree" : "B Sc, MSc",
      "designation" : "Senior Dietician",
      "schedule" : "Mon to Sat: By Appointment"
    } ]
  }, {
    "name" : "Maxillo Facial Surgery",
    "schedules" : [ {
      "doctor" : "Maria John Kuriakose",
      "degree" : "PhD, Certificate in Orthodontics",
      "designation" : "Consultant",
      "schedule" : "Mon to Sat: By Appointment"
    }, {
      "doctor" : "Paul Christadas Salins",
      "degree" : "MDS, BDS, PG. Dip. (Palliative Medicine), FDS RCS (Eng), FFDRCS (Ireland), Advanced Training (Micro Surgery)",
      "designation" : "Chief – Craniomaxillo Facial Surgery, Medical Director & Sr. Vice -President - Mazumdar Shaw Cancer Centre, Narayana Health",
      "schedule" : "Mon to Sat: By Appointment"
    }, {
      "doctor" : "Samarth R Shetty",
      "degree" : "MDS, FFD RCS (Ire), MFDS RCS (Eng)",
      "designation" : "Consultant",
      "schedule" : "Mon to Sat: By Appointment"
    } ]
  }, {
    "name" : "Dermatology And Cosmetology",
    "schedules" : [ {
      "doctor" : "Anuradha Rao",
      "degree" : "MBBS, DNB",
      "designation" : "Visiting Consultant",
      "schedule" : "Mon to Sat: By Appointment"
    }, {
      "doctor" : "Prathibha P M",
      "degree" : "MD",
      "designation" : "Visiting Consultant",
      "schedule" : "Mon to Sat: By Appointment"
    } ]
  }, {
    "name" : "Diabetology",
    "schedules" : [ {
      "doctor" : "Mir Ali Zama",
      "degree" : "MBBS, FIDM (UK)",
      "designation" : "Consultant",
      "schedule" : "Mon to Sat: By Appointment"
    } ]
  }, {
    "name" : "ENT",
    "schedules" : [ {
      "doctor" : "Raghavendra K S",
      "degree" : "DLO, DNB",
      "designation" : "Consultant",
      "schedule" : "Mon to Sat: By Appointment"
    }, {
      "doctor" : "Suhel Hasan",
      "degree" : "MBBS, DLO, MS (ENT), RCS (ENG), FICS",
      "designation" : "Senior Consultant",
      "schedule" : "Mon to Sat: By Appointment"
    } ]
  }, {
    "name" : "Emergency Medicine",
    "schedules" : [ {
      "doctor" : "Srinath Kumar T S",
      "degree" : "MBBS, MD",
      "designation" : "Senior Consultant And Hod",
      "schedule" : "Mon to Sat: By Appointment"
    }, {
      "doctor" : "Viju Wilben. V",
      "degree" : "MD",
      "designation" : "Consultant",
      "schedule" : "Mon to Sat: By Appointment"
    } ]
  }, {
    "name" : "Endocrinology",
    "schedules" : [ {
      "doctor" : "Kranti Shreesh Khadilkar",
      "degree" : "MBBS, MD (General medicine), DM (Endocrinology)",
      "designation" : "Assistant Professor",
      "schedule" : "Mon to Sat: By Appointment"
    }, {
      "doctor" : "Shivaprasad K S",
      "degree" : "MD, DM",
      "designation" : "Consultant",
      "schedule" : "Mon to Sat: By Appointment"
    }, {
      "doctor" : "Subramanian Kannan",
      "degree" : "MBBS, AB (Internal Medicine & Endocrinology)",
      "designation" : "Consultant",
      "schedule" : "Mon to Sat: By Appointment"
    } ]
  }, {
    "name" : "Endocrinology Paediatrics",
    "schedules" : [ {
      "doctor" : "Pavithra Nagaraj",
      "degree" : "MBBS, MD (Paediatric)",
      "designation" : "Consultant",
      "schedule" : "Mon to Sat: By Appointment"
    } ]
  }, {
    "name" : "Gastroenterology - Medical",
    "schedules" : [ {
      "doctor" : "Gayathri Gopalakrishnan",
      "degree" : "MBBS, MD (Internal Medicine), DNB (General Medicine), DNB (Gastroenterology)",
      "designation" : "Consultant - Gastroenterology",
      "schedule" : "Mon to Sat: By Appointment"
    }, {
      "doctor" : "Kiran R",
      "degree" : "MD, DM",
      "designation" : "Consultant",
      "schedule" : "Mon to Sat: By Appointment"
    }, {
      "doctor" : "Nandish H K",
      "degree" : "MBBS, MD, DNB, Fellowship",
      "designation" : "Advanced Therapeutic Endoscopy Fellow",
      "schedule" : "Mon to Sat: By Appointment"
    }, {
      "doctor" : "Rangarajan Kasturi",
      "degree" : "MRCP, FRCP, CCT",
      "designation" : "Consultant",
      "schedule" : "Mon to Sat: By Appointment"
    } ]
  }, {
    "name" : "Gastroenterology - Surgical",
    "schedules" : [ {
      "doctor" : "Ashwinikumar Kudari",
      "degree" : "MS, MCh, MS (General Surgery), MCh (Surgical Gastroenterology), Post Doctoral Fellowship Hepatobiliary Surgery, Fellowship in Advanced Obesity Surgery",
      "designation" : "Senior Consultant",
      "schedule" : "Mon to Sat: By Appointment"
    }, {
      "doctor" : "Chandrasekar Jothiraj",
      "degree" : "MBBS, MS, FRCS, MCh",
      "designation" : "Consultant",
      "schedule" : "Mon to Sat: By Appointment"
    }, {
      "doctor" : "Dhananjay Hm",
      "degree" : "MBBS, AFRCS (General Surgery), MRCS (ED) (General Surgery)",
      "designation" : "Consultant",
      "schedule" : "Mon to Sat: By Appointment"
    }, {
      "doctor" : "Dhananjaya H M",
      "degree" : "MRCS, AFRCS",
      "designation" : "Visiting Consultant",
      "schedule" : "Mon to Sat: By Appointment"
    }, {
      "doctor" : "Sushruth Shetty",
      "degree" : "MBBS, MS (Surgery) MCh (Surgical Gastroenterology), FMAS",
      "designation" : "Associate Consultant",
      "schedule" : "Mon to Sat: By Appointment"
    } ]
  }, {
    "name" : "General Medicine",
    "schedules" : [ {
      "doctor" : "Sonali Ray",
      "degree" : "MD",
      "designation" : "Consultant",
      "schedule" : "Mon to Sat: By Appointment"
    } ]
  }, {
    "name" : "Genetics",
    "schedules" : [ {
      "doctor" : "Siddaramappa J Patil",
      "degree" : "MD, DM",
      "designation" : "Consultant",
      "schedule" : "Mon to Sat: By Appointment"
    } ]
  }, {
    "name" : "Gynaecology - Oncology",
    "schedules" : [ {
      "doctor" : "Rohit Raghunath Ranade",
      "degree" : "MS, MCh",
      "designation" : "Consultant",
      "schedule" : "Mon to Sat: By Appointment"
    } ]
  }, {
    "name" : "Haemato Oncology",
    "schedules" : [ {
      "doctor" : "Nataraj K S",
      "degree" : "MBBS, MD (Internal Medicine), DM (Clinical Hematology & Hematology Oncology, Stem Cell Transplantation)",
      "designation" : "Consultant - Hematology, Hematology - Oncology, Stem Cell Transplant Physician",
      "schedule" : "Mon to Sat: By Appointment"
    }, {
      "doctor" : "Pooja Prakash Mallya",
      "degree" : "MBBS, MD",
      "designation" : "Associate Consultant",
      "schedule" : "Mon to Sat: By Appointment"
    }, {
      "doctor" : "Sharat Damodar",
      "degree" : "DNB (General Medicine), MD, DM (Haematology)",
      "designation" : "Vice Chairman - Oncology Services, Clinical Director - Msmc Senior Consultant & Head Of Adult Haematology And Bmt",
      "schedule" : "Mon to Sat: By Appointment"
    }, {
      "doctor" : "Shilpa Prabhu",
      "degree" : "MBBS, MD, DNB",
      "designation" : "Consultant - Haemato - Oncology",
      "schedule" : "Mon to Sat: By Appointment"
    }, {
      "doctor" : "Shobha Badiger",
      "degree" : "MBBS, MD (Paediatric), DNB (Paediatric), Fellowship in Comprehensive Hemato Oncology, PGDMLE",
      "designation" : "Consultant",
      "schedule" : "Mon to Sat: By Appointment"
    }, {
      "doctor" : "Sunil Bhat",
      "degree" : "MBBS, MD, FPHO",
      "designation" : "Director & Clinical Lead - Paediatric Hematology, Oncology And Blood & Bone Marrow Transplantation",
      "schedule" : "Mon to Sat: By Appointment"
    }, {
      "doctor" : "Vasundhara Kailasnath Posavanika",
      "degree" : "MD, DM, MD, Fellowship Pediatric Hematology, Oncology and Stem Cell Transplantation",
      "designation" : "Consultant",
      "schedule" : "Mon to Sat: By Appointment"
    } ]
  }, {
    "name" : "Head & Neck Surgery - Oncology",
    "schedules" : [ {
      "doctor" : "Jacob P C",
      "degree" : "MDS",
      "designation" : "Visiting Consultant",
      "schedule" : "Mon to Sat: By Appointment"
    }, {
      "doctor" : "Moni Abraham Kuriakose",
      "degree" : "MBCHB, FDSRCS, FFDRCS, FRCS, FRCS Ed, FRCS, MD",
      "designation" : "Visiting Consultant",
      "schedule" : "Mon to Sat: By Appointment"
    }, {
      "doctor" : "Narayana Subramaniam",
      "degree" : "MS, MCh, MRCS, FICRS",
      "designation" : "Consultant",
      "schedule" : "Mon to Sat: By Appointment"
    }, {
      "doctor" : "Vidya Bhushan R",
      "degree" : "MS (ENT), DNB (ENT), FHNS",
      "designation" : "Consultant",
      "schedule" : "Mon to Sat: By Appointment"
    }, {
      "doctor" : "Vijay Pillai",
      "degree" : "MDS, Fellowship (Head and Neck Surgical Oncology), MD (ECFMG)",
      "designation" : "Consultant",
      "schedule" : "Mon to Sat: By Appointment"
    }, {
      "doctor" : "Vivek Shetty",
      "degree" : "MS, Fellowship",
      "designation" : "Associate Consultant",
      "schedule" : "Mon to Sat: By Appointment"
    } ]
  }, {
    "name" : "Infection Medicines",
    "schedules" : [ {
      "doctor" : "George K Varghese",
      "degree" : "MBBS, MD, MSC",
      "designation" : "Senior Consultant",
      "schedule" : "Mon to Sat: By Appointment"
    } ]
  }, {
    "name" : "Internal Medicine",
    "schedules" : [ {
      "doctor" : "George K Varghese",
      "degree" : "MBBS, MD, MSC",
      "designation" : "Senior Consultant",
      "schedule" : "Mon to Sat: By Appointment"
    }, {
      "doctor" : "Hemanth Kumar M",
      "degree" : "MBBS, DTCD, DNB",
      "designation" : "Associate Consultant",
      "schedule" : "Mon to Sat: By Appointment"
    }, {
      "doctor" : "Madhavi K V",
      "degree" : "MBBS, MD (General Medicine), Diploma in Allergy and Asthma",
      "designation" : "Assistant Professor",
      "schedule" : "Mon to Sat: By Appointment"
    }, {
      "doctor" : "Murali Mohan B V",
      "degree" : "MBBS, MD, MRCP",
      "designation" : "Senior Consultant",
      "schedule" : "Mon to Sat: By Appointment"
    }, {
      "doctor" : "Nidhin Mohan",
      "degree" : "MD",
      "designation" : "Consultant",
      "schedule" : "Mon to Sat: By Appointment"
    }, {
      "doctor" : "Nitin Kumar Hegde",
      "degree" : "MBBS, MD (Internal Medicine)",
      "designation" : "Junior Specialist",
      "schedule" : "Mon to Sat: By Appointment"
    }, {
      "doctor" : "Ranjith J",
      "degree" : "MD",
      "designation" : "Consultant",
      "schedule" : "Mon to Sat: By Appointment"
    }, {
      "doctor" : "Ravi Chandra M R K",
      "degree" : "MBBS, DNB",
      "designation" : "Consultant",
      "schedule" : "Mon to Sat: By Appointment"
    } ]
  }, {
    "name" : "Interventional Radiology",
    "schedules" : [ {
      "doctor" : "Chennur S Vikash",
      "degree" : "MD (Radiology) (AIIMS), DNB Radiology, Fellowship in Vascular & Interventional Radiology (Canada), Abdominal Imaging (Canada)",
      "designation" : "Consultant, Director & Head Interventional Radiology",
      "schedule" : "Mon to Sat: By Appointment"
    } ]
  }, {
    "name" : "Kidney Transplant - Adult",
    "schedules" : [ {
      "doctor" : "Krishna Kishore C",
      "degree" : "MBBS, MD (Internal Medicine), DM (Nephrology)",
      "designation" : "Consultant",
      "schedule" : "Mon to Sat: By Appointment"
    }, {
      "doctor" : "Prashanth M Kulkarni",
      "degree" : "MBBS, MS, DNB",
      "designation" : "Consultant",
      "schedule" : "Mon to Sat: By Appointment"
    } ]
  }, {
    "name" : "Kidney Transplant Paediatric",
    "schedules" : [ {
      "doctor" : "Akhila Vasanth Hassan",
      "degree" : "MBBS, DCH, MRCPCH, CCT",
      "designation" : "Consultant",
      "schedule" : "Mon to Sat: By Appointment"
    }, {
      "doctor" : "Ashley Lucien Joseph D’cruz",
      "degree" : "MBBS, MS, MCh",
      "designation" : "Senior Consultant",
      "schedule" : "Mon to Sat: By Appointment"
    }, {
      "doctor" : "Sanjay Rao",
      "degree" : "MS, FRCS, DNB",
      "designation" : "Senior Consultant & Hod",
      "schedule" : "Mon to Sat: By Appointment"
    } ]
  }, {
    "name" : "Lab",
    "schedules" : [ {
      "doctor" : "Girish C J",
      "degree" : "MD",
      "designation" : "Consultant",
      "schedule" : "Mon to Sat: By Appointment"
    }, {
      "doctor" : "Mallika Reddy K",
      "degree" : "MBBS, MD",
      "designation" : "Consultant",
      "schedule" : "Mon to Sat: By Appointment"
    }, {
      "doctor" : "Shaesta Naseem Zaidi",
      "degree" : "MD",
      "designation" : "Consultant",
      "schedule" : "Mon to Sat: By Appointment"
    }, {
      "doctor" : "Suman Roy",
      "degree" : "DCP",
      "designation" : "Consultant",
      "schedule" : "Mon to Sat: By Appointment"
    } ]
  }, {
    "name" : "Liver",
    "schedules" : [ {
      "doctor" : "Sahana Shankar",
      "degree" : "MBBS, MD (Paediatrics), Fellowship (PGHN) (Melbourne, Australia)",
      "designation" : "Consultant",
      "schedule" : "Mon to Sat: By Appointment"
    }, {
      "doctor" : "Somashekara H R",
      "degree" : "MBBS, DCH, DNB, FNB",
      "designation" : "Consultant",
      "schedule" : "Mon to Sat: By Appointment"
    } ]
  }, {
    "name" : "Liver Transplant & Hpb Surgery",
    "schedules" : [ {
      "doctor" : "Manoj Kumar Singh",
      "degree" : "MD (Surgery), FACS, ASTS, Fellowship (Abdominal Organ Transplant Surgery), Fellowship (Advanced Liver Transplant & HPB Surgery)",
      "designation" : "Consultant",
      "schedule" : "Mon to Sat: By Appointment"
    }, {
      "doctor" : "Raghavendra Cv",
      "degree" : "MBBS, MS, DNB, Fellowship in HPB and Liver Transplantation",
      "designation" : "Consultant",
      "schedule" : "Mon to Sat: By Appointment"
    }, {
      "doctor" : "Rajeev Ranjan Sinha",
      "degree" : "MS, FACS, Fellowship (Abdominal Organ Transplant Surgery), Fellowship (American Society of Transplant Surgeons)",
      "designation" : "Consultant",
      "schedule" : "Mon to Sat: By Appointment"
    }, {
      "doctor" : "Sanjay Goja",
      "degree" : "FACS, FEBS (Multiorgan and Liver Transplantation)",
      "designation" : "Program Director And Clinical Lead – Liver Transplant, Hpb Surgery And Robotic Liver Surgery",
      "schedule" : "Mon to Sat: By Appointment"
    } ]
  }, {
    "name" : "Medical Oncology",
    "schedules" : [ {
      "doctor" : "Mansi Khanderia",
      "degree" : "DNB (Internal Medicine), DNB (Medical Oncology), ECMO",
      "designation" : "Consultant",
      "schedule" : "Mon to Sat: By Appointment"
    }, {
      "doctor" : "Nidhi Tandon",
      "degree" : "MD (Medicine), DM (Medical Oncology), Fellowship (Research Hematology), Diploma (Clinical and Translational Sciences)",
      "designation" : "Consultant",
      "schedule" : "Mon to Sat: By Appointment"
    }, {
      "doctor" : "Pragnya Coca",
      "degree" : "MBBS, MD, DM, ESMO",
      "designation" : "Consultant",
      "schedule" : "Mon to Sat: By Appointment"
    }, {
      "doctor" : "Vijay Kumar .S",
      "degree" : "MBBS, MD, DM (Medical Oncology), ECMO, PHD (Tumor Immunology) (Pursuing)",
      "designation" : "Consultant",
      "schedule" : "Mon to Sat: By Appointment"
    } ]
  }, {
    "name" : "Nephrology",
    "schedules" : [ {
      "doctor" : "Ishthiaque Ahmed",
      "degree" : "MBBS, MD, DM",
      "designation" : "Senior Consultant & Transplant Physician",
      "schedule" : "Mon to Sat: By Appointment"
    }, {
      "doctor" : "Krishna Kishore C",
      "degree" : "MBBS, MD (Internal Medicine), DM (Nephrology)",
      "designation" : "Consultant",
      "schedule" : "Mon to Sat: By Appointment"
    }, {
      "doctor" : "Lloyd Vincent",
      "degree" : "MD, DM",
      "designation" : "Visiting Consultant",
      "schedule" : "Mon to Sat: By Appointment"
    }, {
      "doctor" : "Nitin Kumar Hegde",
      "degree" : "MBBS, MD (Internal Medicine)",
      "designation" : "Junior Specialist",
      "schedule" : "Mon to Sat: By Appointment"
    }, {
      "doctor" : "Ram Mohan Sripad Bhat",
      "degree" : "MD (Medicine), MRCP (UK), MRCP (Renal Medicine), CCST (Nephrology)",
      "designation" : "Consultant",
      "schedule" : "Mon to Sat: By Appointment"
    } ]
  }, {
    "name" : "Nephrology - Paediatric",
    "schedules" : [ {
      "doctor" : "Akhila Vasanth Hassan",
      "degree" : "MBBS, DCH, MRCPCH, CCT",
      "designation" : "Consultant",
      "schedule" : "Mon to Sat: By Appointment"
    } ]
  }, {
    "name" : "Neuro Surgery",
    "schedules" : [ {
      "doctor" : "Kiran M",
      "degree" : "MS, MCh, DNB",
      "designation" : "Assistant Professor",
      "schedule" : "Mon to Sat: By Appointment"
    }, {
      "doctor" : "Komal Prasad",
      "degree" : "MBBS, MS (General Surgery), DNB (General Surgery), MCh (Neuro Surgery)",
      "designation" : "Senior Consultant",
      "schedule" : "Mon to Sat: By Appointment"
    }, {
      "doctor" : "Sathyanarayana L D",
      "degree" : "MS, MCh",
      "designation" : "Consultant",
      "schedule" : "Mon to Sat: By Appointment"
    }, {
      "doctor" : "Shibu Vasudevan Pillai",
      "degree" : "MBBS, MCH, Fellowship",
      "designation" : "Senior Consultant",
      "schedule" : "Mon to Sat: By Appointment"
    }, {
      "doctor" : "Sumana B Pallegar",
      "degree" : "MBBS, DNB (Neuro Surgery), Fellow in Epilepsy Surgery and Functional Neuro Surgery",
      "designation" : "Consultant",
      "schedule" : "Mon to Sat: By Appointment"
    }, {
      "doctor" : "Thimappa Hegde",
      "degree" : "MCh",
      "designation" : "Director & Senior Consultant",
      "schedule" : "Mon to Sat: By Appointment"
    } ]
  }, {
    "name" : "Neurology",
    "schedules" : [ {
      "doctor" : "Gopal Krishna Dash",
      "degree" : "MBBS, MD (Medicine), DM (Neuro), PDF (Epilepsy)",
      "designation" : "Consultant - Neurology",
      "schedule" : "Mon to Sat: By Appointment"
    }, {
      "doctor" : "Harirama K Acharya",
      "degree" : "MD, MRCP (UK), MD (Neurology) (USA), Diplomate of American Board of Psychiatry and Neurology",
      "designation" : "Clinical Director - Department Of Neurosciences, Senior Consultant - Neurology",
      "schedule" : "Mon to Sat: By Appointment"
    }, {
      "doctor" : "Kuldeep Shetty",
      "degree" : "MD, DM (Neurology), PDF (Movement Disorder)",
      "designation" : "Junior Consultant",
      "schedule" : "Mon to Sat: By Appointment"
    }, {
      "doctor" : "Radhika Manohar",
      "degree" : "FRCP , CCST",
      "designation" : "Consultant - Neurology",
      "schedule" : "Mon to Sat: By Appointment"
    }, {
      "doctor" : "Tejaswini Patel",
      "degree" : "MBBS, MS ENT, Post Doctoral Fellowship in Neuro Otology",
      "designation" : "Consultant",
      "schedule" : "Mon to Sat: By Appointment"
    }, {
      "doctor" : "Vikram Huded",
      "degree" : "MBBS, MD (General Medicine), DM (Neurology), FINR, Fellow of World Stroke Organisation",
      "designation" : "Senior Consultant",
      "schedule" : "Mon to Sat: By Appointment"
    }, {
      "doctor" : "Vivek Jacob Philip",
      "degree" : "MD, DNB",
      "designation" : "Consultant",
      "schedule" : "Mon to Sat: By Appointment"
    } ]
  }, {
    "name" : "Neurology - Paediatric",
    "schedules" : [ {
      "doctor" : "Minal V. Kekatpure",
      "degree" : "MBBS, MD",
      "designation" : "Senior Consultant",
      "schedule" : "Mon to Sat: By Appointment"
    }, {
      "doctor" : "Tarishi Nemani",
      "degree" : "MBBS, MD (Pediatric), Fellowship (Pediatric Neurology)",
      "designation" : "Associate Consultant",
      "schedule" : "Mon to Sat: By Appointment"
    } ]
  }, {
    "name" : "Nuclear Medicine",
    "schedules" : [ {
      "doctor" : "Sunil H V",
      "degree" : "MD",
      "designation" : "Consultant",
      "schedule" : "Mon to Sat: By Appointment"
    } ]
  }, {
    "name" : "Obstetrics & Gynaecology",
    "schedules" : [ {
      "doctor" : "Anuradha B S",
      "degree" : "MD, DNB, FNB",
      "designation" : "Senior Consultant",
      "schedule" : "Mon to Sat: By Appointment"
    }, {
      "doctor" : "Kiranmayi Setty",
      "degree" : "Masters in OBG",
      "designation" : "Senior Consultant",
      "schedule" : "Mon to Sat: By Appointment"
    }, {
      "doctor" : "Lavanya Kiran",
      "degree" : "MBBS, MS, FRM, MBA, PGDMLE",
      "designation" : "Senior Consultant",
      "schedule" : "Mon to Sat: By Appointment"
    }, {
      "doctor" : "Shakuntala Baliga",
      "degree" : "MD (AIIMS), FICOG",
      "designation" : "Professor & Visiting Senior Consultant",
      "schedule" : "Mon to Sat: By Appointment"
    }, {
      "doctor" : "Srinivas M S",
      "degree" : "MSc, PhD, MSSC",
      "designation" : "Visiting Consultant",
      "schedule" : "Mon to Sat: By Appointment"
    } ]
  }, {
    "name" : "Oncology",
    "schedules" : [ {
      "doctor" : "Akshita Singh",
      "degree" : "MRCS, DNB (General Surgery), Fellowship (Breast Surgical)",
      "designation" : "Consultant",
      "schedule" : "Mon to Sat: By Appointment"
    }, {
      "doctor" : "Jacob P C",
      "degree" : "MDS",
      "designation" : "Visiting Consultant",
      "schedule" : "Mon to Sat: By Appointment"
    }, {
      "doctor" : "Jayant J Bhargav",
      "degree" : "MBBS, DMRT, MSc, MD",
      "designation" : "Junior Consultant",
      "schedule" : "Mon to Sat: By Appointment"
    }, {
      "doctor" : "Mansi Khanderia",
      "degree" : "DNB (Internal Medicine), DNB (Medical Oncology), ECMO",
      "designation" : "Consultant",
      "schedule" : "Mon to Sat: By Appointment"
    }, {
      "doctor" : "Moni Abraham Kuriakose",
      "degree" : "MBCHB, FDSRCS, FFDRCS, FRCS, FRCS Ed, FRCS, MD",
      "designation" : "Visiting Consultant",
      "schedule" : "Mon to Sat: By Appointment"
    }, {
      "doctor" : "Nagaraju Morubagal",
      "degree" : "DA, FCARCSI",
      "designation" : "Visiting Consultant",
      "schedule" : "Mon to Sat: By Appointment"
    }, {
      "doctor" : "Narayana Subramaniam",
      "degree" : "MS, MCh, MRCS, FICRS",
      "designation" : "Consultant",
      "schedule" : "Mon to Sat: By Appointment"
    }, {
      "doctor" : "Nataraj Ks",
      "degree" : "MBBS, MD (Internal Medicine), DM (Clinical Hematology & Hematology Oncology, Stem Cell Transplantation)",
      "designation" : "Consultant - Hematology, Hematology - Oncology, Stem Cell Transplant Physician",
      "schedule" : "Mon to Sat: By Appointment"
    }, {
      "doctor" : "Nidhi Tandon",
      "degree" : "MD (Medicine), DM (Medical Oncology), Fellowship (Research Hematology), Diploma (Clinical and Translational Sciences)",
      "designation" : "Consultant",
      "schedule" : "Mon to Sat: By Appointment"
    }, {
      "doctor" : "Pooja Prakash Mallya",
      "degree" : "MBBS, MD",
      "designation" : "Associate Consultant",
      "schedule" : "Mon to Sat: By Appointment"
    }, {
      "doctor" : "Pragnya Coca",
      "degree" : "MBBS, MD, DM, ESMO",
      "designation" : "Consultant",
      "schedule" : "Mon to Sat: By Appointment"
    }, {
      "doctor" : "Rohit Raghunath Ranade",
      "degree" : "MS, MCh",
      "designation" : "Consultant",
      "schedule" : "Mon to Sat: By Appointment"
    }, {
      "doctor" : "Saurabha Kumar",
      "degree" : "MD",
      "designation" : "Consultant",
      "schedule" : "Mon to Sat: By Appointment"
    }, {
      "doctor" : "Sharat Damodar",
      "degree" : "DNB (General Medicine), MD, DM (Haematology)",
      "designation" : "Vice Chairman - Oncology Services, Clinical Director - Msmc Senior Consultant & Head Of Adult Haematology And Bmt",
      "schedule" : "Mon to Sat: By Appointment"
    }, {
      "doctor" : "Shilpa Prabhu",
      "degree" : "MBBS, MD, DNB",
      "designation" : "Consultant - Haemato - Oncology",
      "schedule" : "Mon to Sat: By Appointment"
    }, {
      "doctor" : "Shobha Badiger",
      "degree" : "MBBS, MD (Paediatric), DNB (Paediatric), Fellowship in Comprehensive Hemato Oncology, PGDMLE",
      "designation" : "Consultant",
      "schedule" : "Mon to Sat: By Appointment"
    }, {
      "doctor" : "Suman M B",
      "degree" : "MS (Orthopaedics), Fellowship in Musculo Skeletal Oncology",
      "designation" : "Consultant",
      "schedule" : "Mon to Sat: By Appointment"
    }, {
      "doctor" : "Sunil Bhat",
      "degree" : "MBBS, MD, FPHO",
      "designation" : "Director & Clinical Lead - Paediatric Hematology, Oncology And Blood & Bone Marrow Transplantation",
      "schedule" : "Mon to Sat: By Appointment"
    }, {
      "doctor" : "Vasundhara Kailasnath Posavanika",
      "degree" : "MD, DM, MD, Fellowship Pediatric Hematology, Oncology and Stem Cell Transplantation",
      "designation" : "Consultant",
      "schedule" : "Mon to Sat: By Appointment"
    }, {
      "doctor" : "Vidya Bhushan R",
      "degree" : "MS (ENT), DNB (ENT), FHNS",
      "designation" : "Consultant",
      "schedule" : "Mon to Sat: By Appointment"
    }, {
      "doctor" : "Vijay Kumar .S",
      "degree" : "MBBS, MD, DM (Medical Oncology), ECMO, PHD (Tumor Immunology) (Pursuing)",
      "designation" : "Consultant",
      "schedule" : "Mon to Sat: By Appointment"
    }, {
      "doctor" : "Vijay Pillai",
      "degree" : "MDS, Fellowship (Head and Neck Surgical Oncology), MD (ECFMG)",
      "designation" : "Consultant",
      "schedule" : "Mon to Sat: By Appointment"
    }, {
      "doctor" : "Vivek Shetty",
      "degree" : "MS, Fellowship",
      "designation" : "Associate Consultant",
      "schedule" : "Mon to Sat: By Appointment"
    } ]
  }, {
    "name" : "Ortho - Oncology",
    "schedules" : [ {
      "doctor" : "Suman M B",
      "degree" : "MS (Orthopaedics), Fellowship in Musculo Skeletal Oncology",
      "designation" : "Consultant",
      "schedule" : "Mon to Sat: By Appointment"
    } ]
  }, {
    "name" : "Paediatric Liver Transplant",
    "schedules" : [ {
      "doctor" : "Ashley Lucien Joseph D’cruz",
      "degree" : "MBBS, MS, MCh",
      "designation" : "Senior Consultant",
      "schedule" : "Mon to Sat: By Appointment"
    }, {
      "doctor" : "Sahana Shankar",
      "degree" : "MBBS, MD (Paediatrics), Fellowship (PGHN) (Melbourne, Australia)",
      "designation" : "Consultant",
      "schedule" : "Mon to Sat: By Appointment"
    }, {
      "doctor" : "Sanjay Rao",
      "degree" : "MS, FRCS, DNB",
      "designation" : "Senior Consultant & Hod",
      "schedule" : "Mon to Sat: By Appointment"
    }, {
      "doctor" : "Somashekara H R",
      "degree" : "MBBS, DCH, DNB, FNB",
      "designation" : "Consultant",
      "schedule" : "Mon to Sat: By Appointment"
    }, {
      "doctor" : "Vinay Chandrashekar",
      "degree" : "MS, MCh",
      "designation" : "Consultant",
      "schedule" : "Mon to Sat: By Appointment"
    }, {
      "doctor" : "Zameer M M",
      "degree" : "MS, MCh, MRCS (Edinburgh)",
      "designation" : "Senior Consultant Pediatric Surgeon",
      "schedule" : "Mon to Sat: By Appointment"
    } ]
  }, {
    "name" : "Paediatric Oncology",
    "schedules" : [ {
      "doctor" : "Shobha Badiger",
      "degree" : "MBBS, MD (Paediatric), DNB (Paediatric), Fellowship in Comprehensive Hemato Oncology, PGDMLE",
      "designation" : "Consultant",
      "schedule" : "Mon to Sat: By Appointment"
    }, {
      "doctor" : "Sunil Bhat",
      "degree" : "MBBS, MD, FPHO",
      "designation" : "Director & Clinical Lead - Paediatric Hematology, Oncology And Blood & Bone Marrow Transplantation",
      "schedule" : "Mon to Sat: By Appointment"
    }, {
      "doctor" : "Vasundhara Kailasnath Posavanika",
      "degree" : "MD, DM, MD, Fellowship Pediatric Hematology, Oncology and Stem Cell Transplantation",
      "designation" : "Consultant",
      "schedule" : "Mon to Sat: By Appointment"
    } ]
  }, {
    "name" : "Paediatric Surgery",
    "schedules" : [ {
      "doctor" : "Ashley Lucien Joseph D’cruz",
      "degree" : "MBBS, MS, MCh",
      "designation" : "Senior Consultant",
      "schedule" : "Mon to Sat: By Appointment"
    }, {
      "doctor" : "Sanjay Rao",
      "degree" : "MS, FRCS, DNB",
      "designation" : "Senior Consultant & Hod",
      "schedule" : "Mon to Sat: By Appointment"
    }, {
      "doctor" : "Vinay Chandrashekar",
      "degree" : "MS, MCh",
      "designation" : "Consultant",
      "schedule" : "Mon to Sat: By Appointment"
    }, {
      "doctor" : "Zameer M M",
      "degree" : "MS, MCh, MRCS (Edinburgh)",
      "designation" : "Senior Consultant Pediatric Surgeon",
      "schedule" : "Mon to Sat: By Appointment"
    } ]
  }, {
    "name" : "Paediatrics",
    "schedules" : [ {
      "doctor" : "Akhila Vasanth Hassan",
      "degree" : "MBBS, DCH, MRCPCH, CCT",
      "designation" : "Consultant",
      "schedule" : "Mon to Sat: By Appointment"
    }, {
      "doctor" : "Anil Kumar Sapare",
      "degree" : "MBBS, DCH, DNB, Certification in Specialist Training, MRCPCH",
      "designation" : "Consultant - Pulmonologist",
      "schedule" : "Mon to Sat: By Appointment"
    }, {
      "doctor" : "Harini Sreedharan",
      "degree" : "DNB, Fellowship in Neonatology",
      "designation" : "Consultant",
      "schedule" : "Mon to Sat: By Appointment"
    }, {
      "doctor" : "Hiremath Sagar",
      "degree" : "MBBS, MD (Pediatrics), Fellow in Pediatric Intensive Care",
      "designation" : "Consultant - Paediatrics",
      "schedule" : "Mon to Sat: By Appointment"
    }, {
      "doctor" : "Prasanna C.s",
      "degree" : "MBBS, MRCP (Psych), CCT (UK)",
      "designation" : "Consultant",
      "schedule" : "Mon to Sat: By Appointment"
    }, {
      "doctor" : "Rajiv Aggarwal",
      "degree" : "MD, Fellowship",
      "designation" : "Senior Consultant",
      "schedule" : "Mon to Sat: By Appointment"
    }, {
      "doctor" : "Rashmi B V",
      "degree" : "MBBS, DNB (Pediatrics), MRCPCH (UK)",
      "designation" : "Consultant",
      "schedule" : "Mon to Sat: By Appointment"
    } ]
  }, {
    "name" : "Pain",
    "schedules" : [ {
      "doctor" : "Nagaraju Morubagal",
      "degree" : "DA, FCARCSI",
      "designation" : "Visiting Consultant",
      "schedule" : "Mon to Sat: By Appointment"
    } ]
  }, {
    "name" : "Physiotherapy & Rehabilitation",
    "schedules" : [ {
      "doctor" : "Sukumar S V",
      "degree" : "BPT, MPT",
      "designation" : "Senior Physiotherapist",
      "schedule" : "Mon to Sat: By Appointment"
    }, {
      "doctor" : "V Ramakrishna Rao P T",
      "degree" : "MPT",
      "designation" : "Hod & Consultant",
      "schedule" : "Mon to Sat: By Appointment"
    } ]
  }, {
    "name" : "Plastic Surgery",
    "schedules" : [ {
      "doctor" : "Kiran S Petkar",
      "degree" : "MBBS, MS (General Surgeryery), MCh (Plastic Surgery), DNB (Plastic Surgery)",
      "designation" : "Visiting Consultant",
      "schedule" : "Mon to Sat: By Appointment"
    }, {
      "doctor" : "Sachin Uttam Chavre",
      "degree" : "DNB (General Surgery), DNB (Plastic Surgery)",
      "designation" : "Consultant",
      "schedule" : "Mon to Sat: By Appointment"
    } ]
  }, {
    "name" : "Psychiatry & Clinical Psychology",
    "schedules" : [ {
      "doctor" : "Prasanna C.s",
      "degree" : "MBBS, MRCP Psych CCT (UK)",
      "designation" : "Consultant",
      "schedule" : "Mon to Sat: By Appointment"
    }, {
      "doctor" : "Rekha Robbie",
      "degree" : "MBBS, PHD, MRPS",
      "designation" : "Consultant",
      "schedule" : "Mon to Sat: By Appointment"
    }, {
      "doctor" : "Shailaja Christina",
      "degree" : "MSc, Mphil",
      "designation" : "Visiting Consultant",
      "schedule" : "Mon to Sat: By Appointment"
    }, {
      "initial" : "Ms.",
      "doctor" : "Raina Jane D'mello",
      "degree" : "M.Phil Clinical Psychology, MSc",
      "designation" : "Consultant",
      "schedule" : "Mon to Sat: By Appointment"
    } ]
  }, {
    "name" : "Pulmonology",
    "schedules" : [ {
      "doctor" : "Anil Kumar Sapare",
      "degree" : "MBBS, DCH, DNB, Certification in Specialist Training, MRCPCH",
      "designation" : "Consultant - Pulmonologist",
      "schedule" : "Mon to Sat: By Appointment"
    }, {
      "doctor" : "Basha J Khan",
      "degree" : "MD, ISCCM, MRCP",
      "designation" : "Senior Consultant",
      "schedule" : "Mon to Sat: By Appointment"
    }, {
      "doctor" : "Hemanth Kumar M",
      "degree" : "MBBS, DTCD, DNB",
      "designation" : "Associate Consultant",
      "schedule" : "Mon to Sat: By Appointment"
    }, {
      "doctor" : "Ishan Ashok Capoor",
      "degree" : "MD (Respiratory Medicine)",
      "designation" : "Consultant",
      "schedule" : "Mon to Sat: By Appointment"
    }, {
      "doctor" : "Kedar R Hibare",
      "degree" : "MBBS, FCCP, Fellowship (Interventional Pulmonology & Thoracic Oncology), DNB (Resp Diseases), FCCP (Interventional Pulmonology)",
      "designation" : "Junior Consultant",
      "schedule" : "Mon to Sat: By Appointment"
    }, {
      "doctor" : "Murali Mohan B V",
      "degree" : "MBBS, MD, MRCP",
      "designation" : "Senior Consultant",
      "schedule" : "Mon to Sat: By Appointment"
    }, {
      "doctor" : "Ranganatha R",
      "degree" : "DTCD, DNB",
      "designation" : "Consultant",
      "schedule" : "Mon to Sat: By Appointment"
    }, {
      "doctor" : "Ravi Chandra M R K",
      "degree" : "MBBS, DNB",
      "designation" : "Consultant",
      "schedule" : "Mon to Sat: By Appointment"
    }, {
      "doctor" : "Syed Zulkharnain Tousheed",
      "degree" : "MBBS, MD",
      "designation" : "Consultant",
      "schedule" : "Mon to Sat: By Appointment"
    } ]
  }, {
    "name" : "Radiation Oncology",
    "schedules" : [ {
      "doctor" : "Jayant J Bhargav",
      "degree" : "MBBS, DMRT, MSc, MD",
      "designation" : "Junior Consultant",
      "schedule" : "Mon to Sat: By Appointment"
    }, {
      "doctor" : "Saurabha Kumar",
      "degree" : "MD",
      "designation" : "Consultant",
      "schedule" : "Mon to Sat: By Appointment"
    } ]
  }, {
    "name" : "Radiology",
    "schedules" : [ {
      "doctor" : "Karthik G A",
      "degree" : "MD",
      "designation" : "Consultant",
      "schedule" : "Mon to Sat: By Appointment"
    }, {
      "doctor" : "Kishore Kumar B N",
      "degree" : "DMRD, MD, PGDMLE",
      "designation" : "Senior Consultant",
      "schedule" : "Mon to Sat: By Appointment"
    }, {
      "doctor" : "Prathibha Bandgar",
      "degree" : "MD",
      "designation" : "Consultant",
      "schedule" : "Mon to Sat: By Appointment"
    }, {
      "doctor" : "Santhosh D G",
      "degree" : "DNB",
      "designation" : "Consultant",
      "schedule" : "Mon to Sat: By Appointment"
    }, {
      "doctor" : "Shri Harsha Krishna",
      "degree" : "DNB",
      "designation" : "Consultant",
      "schedule" : "Mon to Sat: By Appointment"
    }, {
      "doctor" : "Tanuj Gupta",
      "degree" : "DMRD, DNB",
      "designation" : "Consultant",
      "schedule" : "Mon to Sat: By Appointment"
    }, {
      "doctor" : "Venkatraman Bhat",
      "degree" : "MD, MNAMS, FRCR",
      "designation" : "Senior Consultant",
      "schedule" : "Mon to Sat: By Appointment"
    }, {
      "doctor" : "Vidhya Thagamani",
      "degree" : "MD, MBBS, DNB (Radiodiagnosis)",
      "designation" : "Consultant",
      "schedule" : "Mon to Sat: By Appointment"
    }, {
      "doctor" : "Vidya T",
      "degree" : "MD",
      "designation" : "Consultant",
      "schedule" : "Mon to Sat: By Appointment"
    }, {
      "doctor" : "Vimal Raj J",
      "degree" : "FRCR, PGDMLS, EDM",
      "designation" : "Consultant",
      "schedule" : "Mon to Sat: By Appointment"
    } ]
  }, {
    "name" : "Rheumatology",
    "schedules" : [ {
      "doctor" : "Aruna Bhat",
      "degree" : "DCH, MRCPCH",
      "designation" : "Consultant",
      "schedule" : "Mon to Sat: By Appointment"
    }, {
      "doctor" : "Manisha Ashwin Daware",
      "degree" : "MBBS, MD (General Medicine), DNB (Generla Medicine)",
      "designation" : "Consultant",
      "schedule" : "Mon to Sat: By Appointment"
    }, {
      "doctor" : "Pradeep R Kumar",
      "degree" : "MBBS, MRCP, MD, FRCP, CCT",
      "designation" : "Senior Consultant",
      "schedule" : "Mon to Sat: By Appointment"
    } ]
  }, {
    "name" : "Robotic Surgery",
    "schedules" : [ {
      "doctor" : "Ashwinikumar Kudari",
      "degree" : "MS, MCh, MS (General Surgery), MCh (Surgical Gastroenterology), Postdoctoral Fellowship Hepatobiliary Surgery, Fellowship in Advanced Obesity Surgery",
      "designation" : "Senior Consultant",
      "schedule" : "Mon to Sat: By Appointment"
    }, {
      "doctor" : "Narayana Subramaniam",
      "degree" : "MS, MCh, MRCS, FICRS",
      "designation" : "Consultant",
      "schedule" : "Mon to Sat: By Appointment"
    }, {
      "doctor" : "Prashanth M Kulkarni",
      "degree" : "MBBS, MS, DNB",
      "designation" : "Consultant",
      "schedule" : "Mon to Sat: By Appointment"
    }, {
      "doctor" : "Rohit Raghunath Ranade",
      "degree" : "MS, MCh",
      "designation" : "Consultant",
      "schedule" : "Mon to Sat: By Appointment"
    } ]
  }, {
    "name" : "Speech And Swallow Rehabilitation",
    "schedules" : [ {
      "doctor" : "Smita Caren Mathias",
      "degree" : "BSc (Speech & Hearing), MSc (Audiology & Speech Language Pathology)",
      "designation" : "Senior Speech & Swallow Therapist",
      "schedule" : "Mon to Sat: By Appointment"
    } ]
  }, {
    "name" : "Thoracic Surgery",
    "schedules" : [ {
      "doctor" : "Srikrishna S V",
      "degree" : "MS, MCh",
      "designation" : "Senior Consultant",
      "schedule" : "Mon to Sat: By Appointment"
    }, {
      "doctor" : "Vijay C L",
      "degree" : "MS, DNB",
      "designation" : "Consultant",
      "schedule" : "Mon to Sat: By Appointment"
    } ]
  }, {
    "name" : "Urology",
    "schedules" : [ {
      "doctor" : "Hasit Rudresh Kumar Mehta",
      "degree" : "MBBS, MS, DNB, MNAMS",
      "designation" : "Senior Consultant",
      "schedule" : "Mon to Sat: By Appointment"
    }, {
      "doctor" : "Prashanth M Kulkarni",
      "degree" : "MBBS, MS, DNB",
      "designation" : "Consultant",
      "schedule" : "Mon to Sat: By Appointment"
    }, {
      "doctor" : "Saurabh Bhargava",
      "degree" : "MBBS, MRCS, MD, FRCS (Urology)",
      "designation" : "Senior Consultant",
      "schedule" : "Mon to Sat: By Appointment"
    } ]
  }, {
    "name" : "Vascular Surgery",
    "schedules" : [ {
      "doctor" : "Rajesh S",
      "degree" : "MS, MRCS, FEVS",
      "designation" : "Consultant",
      "schedule" : "Mon to Sat: By Appointment"
    }, {
      "doctor" : "Robbie George",
      "degree" : "MS, PDCC, DNB, FRCS",
      "designation" : "Senior Consultant",
      "schedule" : "Mon to Sat: By Appointment"
    }, {
      "doctor" : "Saurabh Rai",
      "degree" : "MBBS, MS, FRCS",
      "designation" : "Consultant",
      "schedule" : "Mon to Sat: By Appointment"
    } ]
  } ]
}