{
  "name" : "Madhukar Rainbow Children’s Hospital",
  "specialties" : [ {
    "name" : "Anaesthesiology",
    "schedules" : [ {
      "doctor" : "Rakhee Goyal",
      "degree" : "MBBS, MD (Anaesthesia), Speciization in Pediatric Anaesthesia",
      "schedule" : "Mon to Sat: By Appointment"
    } ]
  }, {
    "name" : "Dermatology",
    "schedules" : [ {
      "doctor" : "Rashmi Sharma",
      "degree" : "MBBS, DDVL, DNB (Dermatology & Venereology)",
      "schedule" : "Tue, Thu, Sat: 11:00 AM - 12:00 PM"
    } ]
  }, {
    "name" : "Endocrinology",
    "schedules" : [ {
      "doctor" : "Swati Kanodia",
      "degree" : "MBBS, MD (Pediatrics), Fellowship in Pediatric & Adolescent Endocrinology & Diabetes (European Society Of Pediatric Endocrinology)",
      "schedule" : "Mon, Thu: By Appointment"
    } ]
  }, {
    "name" : "Fetal Medicine",
    "schedules" : [ {
      "doctor" : "Chanchal",
      "degree" : "MBBS, MD (Obstetrics & Gynaecology), MRCOG (UK), Fellowship in Maternal Fetal Medicine, Fetal Medicine Foundation Certified (NUH, Singapore)",
      "schedule" : "Mon to Sat: 02:00 PM - 05:00 PM"
    } ]
  }, {
    "name" : "Obstetrics & Gynaecology",
    "schedules" : [ {
      "doctor" : "Jayasree Sundar",
      "degree" : "MBBS, DGO, MRCOG , FRCOG",
      "schedule" : "Mon to Thu: 09:00 AM - 02:00 PM\nFri: 10:00 AM - 02:00 PM\nSat: 08:00 AM - 02:00 PM"
    }, {
      "doctor" : "Meenakshi Banerjee",
      "degree" : "MBBS, MS (Obstetrics & Gynaecology)",
      "schedule" : "Mon, Thu: 12:00 PM - 04:00 PM\nTue: 10:00 AM - 02:00 PM\nWed, Fri: 08:00 AM - 12:00 PM\nSat: 02:00 PM - 06:00 PM"
    }, {
      "doctor" : "C S Mythreyi",
      "degree" : "MBBS, DGO, DNB (Obstetrics & Gynaecology)",
      "schedule" : "Mon, Thu, Sat: 08:00 AM - 12:00 PM\nTue: 02:00 PM - 06:00 PM\nWed, Fri: 12:00 PM - 04:00 PM"
    }, {
      "doctor" : "Neha Khandelwal",
      "degree" : "MBBS, MS (Obstetrics & Gynecology)",
      "schedule" : "Mon, Sat: 09:00 AM - 01:00 PM\nTue, Thu: 11:00 AM - 03:00 PM\nWed, Fri: 10:00 AM - 02:00 PM"
    }, {
      "doctor" : "Sakshi Goel Chakraborty",
      "degree" : "MS (Obstetrics & Gynecology)",
      "schedule" : "Mon: 08:00 AM - 09:00 AM, 02:00 PM - 06:00 PM\nTue: 08:00 AM - 11:00 AM\nWed: 08:00 AM - 12:00 PM\nThu: 04:00 PM - 08:00 PM\nFri: 08:00 AM - 10:00 AM, 02:00 PM - 04:00 PM\nSat: 08:00 AM - 10:00 AM, 04:00 PM - 06:00 PM"
    }, {
      "doctor" : "Ashima Gulia",
      "degree" : "MD, DNB (Obstetrics & Gynecology)",
      "schedule" : "Mon: 09:00 AM - 01:00 PM\nTue: 10:00 AM - 02:00 PM\nWed, Fri: 12:00 PM - 04:00 PM\nThu, Sat: 04:00 PM - 08:00 PM"
    }, {
      "doctor" : "Alka Gujral",
      "degree" : "MS (Obstetrics & Gynecology), Diploma in Minimally Invasive Surgery",
      "schedule" : "Mon, Wed, Fri, Sat: 10:00 AM - 02:00 PM\nTue, Thu: 12:00 PM - 04:00 PM"
    } ]
  }, {
    "name" : "Paediatric",
    "schedules" : [ {
      "doctor" : "Anamika Dubey",
      "degree" : "MBBS, MD (Pediatrics)",
      "schedule" : "Mon to Fri: 10:30 AM - 02:00 PM, 05:00 PM - 08:00 PM\nSat: 10:30 AM - 02:00 PM"
    }, {
      "doctor" : "Mona Kulpati",
      "degree" : "MBBS, DCH, MRCPCH (Royal College of Pediatrics & Child Health) (UK)",
      "schedule" : "Mon to Sat: 06:00 PM - 08:00 PM"
    }, {
      "doctor" : "Praveen Khilnani",
      "degree" : "MD, FAAP, FCCM, FSICCM, MCCM (USA), Diploma at American board of Pediatric & Pediatric critical care medicine",
      "schedule" : "Mon to Sat: 02:00 PM - 06:00 PM"
    }, {
      "doctor" : "Anjali Saxena",
      "degree" : "MBBS, MD (Pediatrics)",
      "schedule" : "Mon, Tue, Thu, Fri, Sat: 09:30 AM - 01:00 PM, 05:00 PM - 08:00 PM\nWed: 09:30 AM - 01:00 PM"
    }, {
      "doctor" : "Arvind Taneja",
      "degree" : "MBBS, MD (Pediatrics), Diplomate of the American Board of Pediatrics, Fellowship in Infectious Diseases",
      "schedule" : "Mon to Fri: 01:00 PM - 03:00 PM"
    }, {
      "doctor" : "Vidya Poonacha Taneja",
      "degree" : "MBBS, MD (Pediatrics)",
      "schedule" : "Mon to Fri: 01:00 PM - 03:00 PM"
    }, {
      "doctor" : "Sisir Paul",
      "degree" : "MBBS, MD (Pediatrics)",
      "schedule" : "Mon to Sat: 11:00 AM - 01:00 PM"
    }, {
      "doctor" : "S K Nakra",
      "degree" : "MBBS, DCH, MD (Pediatrics)",
      "schedule" : "Mon to Sat: 11:00 AM - 01:30 PM"
    }, {
      "doctor" : "Nitin Verma",
      "degree" : "MBBS, MD (Pediatrics)",
      "schedule" : "Mon to Sat: 11:00 AM - 01:00 PM"
    }, {
      "doctor" : "Shambhavi Seth",
      "degree" : "MBBS, DNB (Pediatrics), PG Diploma (Developmental Neurology)",
      "schedule" : "Mon to Sat: By Appointment"
    }, {
      "doctor" : "Himani Khanna Narula",
      "degree" : "MBBS, DCH, PG Diploma (Developmental Neurology)",
      "schedule" : "Fri: 02:00 PM - 04:00 PM"
    }, {
      "doctor" : "Rajiv Kumar Malik",
      "degree" : "MD (Pediatrics)",
      "schedule" : "Mon to Sat: By Appointment"
    } ]
  }, {
    "name" : "Paediatric Cardiology",
    "schedules" : [ {
      "doctor" : "Vikas Kohli",
      "degree" : "MBBS, MD (Pediatrics), Fellowship In Pediatric Cardiology American Board Certified",
      "schedule" : "Mon: 06:00 PM - 07:00 PM\nTue: 09:00 AM - 10:00 AM"
    } ]
  }, {
    "name" : "Paediatric ENT",
    "schedules" : [ {
      "doctor" : "Anup Sabherwal",
      "degree" : "MBBS, MS (ENT)",
      "schedule" : "Mon to Sat: 09:00 AM - 10:00 AM, 05:00 PM - 06:00 PM"
    } ]
  }, {
    "name" : "Paediatric ICU",
    "schedules" : [ {
      "doctor" : "Praveen Khilnani",
      "degree" : "MD, FAAP, FCCM, FSICCM, MCCM (USA), Diploma at American board of Pediatric & Pediatric critical care medicine",
      "schedule" : "Mon to Sat: 02:00 PM - 06:00 PM"
    } ]
  }, {
    "name" : "Paediatric Neurology",
    "schedules" : [ {
      "doctor" : "Ramandeep S. Dang",
      "degree" : "MBBS, MS (Surgery), MCh (Neurosurgery)",
      "schedule" : "Mon to Sat: By Appointment"
    } ]
  }, {
    "name" : "Paediatric Pulmonology",
    "schedules" : [ {
      "doctor" : "Praveen Khilnani",
      "degree" : "MD, FAAP, FCCM, FSICCM, MCCM(USA), Diploma at American board of Pediatric & Pediatric critical care medicine",
      "schedule" : "Mon to Sat: 02:00 PM - 06:00 PM"
    }, {
      "doctor" : "Premila Paul",
      "degree" : "MBBS, DCh, MD (Pediatrics)",
      "schedule" : "Mon, Wed: 01:00 PM - 03:00 PM\nFri: 01:00 PM - 02:00 PM"
    } ]
  }, {
    "name" : "Paediatric Surgery",
    "schedules" : [ {
      "doctor" : "Rakesh Handa",
      "degree" : "MBBS, MS, MCh (Pediatric Surgery), DNB (Pediatric Surgery), FAIS, FIAPS",
      "schedule" : "Tue, Sat: 02:00 PM - 04:00 PM\nThu: 10:00 AM - 12:00 PM, 02:00 PM - 04:00 PM"
    }, {
      "doctor" : "Meera Luthra",
      "degree" : "MBBS, MS (General Surgery), MCh (Pediatrics Surgery), Clinical Fellowship (Royal Children’s Hospital, Melbourne)",
      "schedule" : "Wed: 09:00 AM - 10:00 AM, 02:00 PM - 04:00 PM\nSat: 09:00 AM - 10:00 AM"
    } ]
  }, {
    "name" : "Paediatric Urology",
    "schedules" : [ {
      "doctor" : "Yashpal Singh Dhaiya",
      "degree" : "MBBS, MD (Radiology)",
      "schedule" : "Mon to Sat: By Appointment"
    }, {
      "doctor" : "Rachita Gupta",
      "degree" : "MBBS, DNB (Radio Diagnosis)",
      "schedule" : "Mon to Sat: By Appointment"
    } ]
  } ]
}